{"_id":{"$oid":"635565e632a06674161834a3"},"username":"b","password":"123","fullname":"a","__v":0}
{"_id":{"$oid":"6355673032a06674161834a8"},"username":"c","password":"123","fullname":"a","__v":0}
{"_id":{"$oid":"635567d432a06674161834ab"},"username":"a","password":"123","fullname":"abc","__v":0}
{"_id":{"$oid":"63556d9732a06674161834b1"},"username":"e","password":"123","fullname":"eagle","__v":0}
{"_id":{"$oid":"635acae3bfa0745590971759"},"username":"me","password":"12345","fullnane":"I am me"}
{"_id":{"$oid":"635acba7bfa074559097175a"},"username":"me","password":"12345","fullnane":"I am me"}
